android_env/__init__.py
android_env/environment.py
android_env/environment_test.py
android_env/loader.py
android_env/loader_test.py
android_env/utils.py
android_env/components/__init__.py
android_env/components/action_type.py
android_env/components/adb_controller.py
android_env/components/adb_controller_test.py
android_env/components/adb_log_stream.py
android_env/components/adb_log_stream_test.py
android_env/components/app_screen_checker.py
android_env/components/app_screen_checker_test.py
android_env/components/coordinator.py
android_env/components/coordinator_test.py
android_env/components/dumpsys_thread.py
android_env/components/dumpsys_thread_test.py
android_env/components/errors.py
android_env/components/event_listeners.py
android_env/components/log_stream.py
android_env/components/log_stream_test.py
android_env/components/logcat_thread.py
android_env/components/logcat_thread_test.py
android_env/components/screen_analyzer_thread.py
android_env/components/setup_step_interpreter.py
android_env/components/setup_step_interpreter_test.py
android_env/components/specs.py
android_env/components/specs_test.py
android_env/components/task_manager.py
android_env/components/task_manager_test.py
android_env/components/thread_function.py
android_env/components/thread_function_test.py
android_env/components/utils.py
android_env/components/utils_test.py
android_env/components/vh_analyzer_thread.py
android_env/components/simulators/__init__.py
android_env/components/simulators/base_simulator.py
android_env/components/simulators/base_simulator_test.py
android_env/components/simulators/emulator/__init__.py
android_env/components/simulators/emulator/emulator_launcher.py
android_env/components/simulators/emulator/emulator_launcher_test.py
android_env/components/simulators/emulator/emulator_simulator.py
android_env/components/simulators/emulator/emulator_simulator_test.py
android_env/components/simulators/fake/__init__.py
android_env/components/simulators/fake/fake_simulator.py
mobile_env_rl-4.0.dist-info/LICENSE
mobile_env_rl-4.0.dist-info/METADATA
mobile_env_rl-4.0.dist-info/WHEEL
mobile_env_rl-4.0.dist-info/top_level.txt
mobile_env_rl-4.0.dist-info/RECORD
