Metadata-Version: 2.1
Name: mobile-env-rl
Version: 4.0
Summary: A Universal Platform for Training and Evaluation of Mobile Interaction
Home-page: https://github.com/X-LANCE/Mobile-Env
Author: Danyang Zhang @X-Lance
Author-email: "Danyang Zhang @X-Lance" <zdy004007@126.com>
License: 
Project-URL: Homepage, https://github.com/X-LANCE/Mobile-Env
Keywords: InfoUI interaction
Classifier: Programming Language :: Python :: 3
Classifier: License :: OSI Approved :: Apache Software License
Requires-Python: >=3.7
License-File: LICENSE
Requires-Dist: absl-py >=0.1.0
Requires-Dist: grpcio
Requires-Dist: mock
Requires-Dist: numpy
Requires-Dist: pexpect >=4.8.0
Requires-Dist: portpicker >=1.2.0
Requires-Dist: protobuf >=2.6
Requires-Dist: lxml
Requires-Dist: torch
Requires-Dist: torchvision
Requires-Dist: transformers
Requires-Dist: requests
Requires-Dist: Flask
Requires-Dist: Flask-Compress
Requires-Dist: cssselect
Requires-Dist: rapidfuzz
Requires-Dist: sentence-transformers
Provides-Extra: dmenv
Requires-Dist: dm-env ; extra == 'dmenv'
Provides-Extra: easyocr
Requires-Dist: easyocr ; extra == 'easyocr'
Provides-Extra: gym
Requires-Dist: gymnasium ; extra == 'gym'
Provides-Extra: pygame
Requires-Dist: pygame ; extra == 'pygame'
Provides-Extra: testing
Requires-Dist: attrs ==20.3.0 ; extra == 'testing'
Requires-Dist: pillow ; extra == 'testing'
Requires-Dist: pytype ; extra == 'testing'
Requires-Dist: pytest-xdist ; extra == 'testing'
